LICENSE
quepland_bot/__init__.py
quepland_bot/application/__init__.py
quepland_bot/application/exceptions/__init__.py
quepland_bot/application/exceptions/application_exception.py
quepland_bot/application/exceptions/coordinates_sequence_not_found_exception.py
quepland_bot/domain/__init__.py
quepland_bot/domain/entities/__init__.py
quepland_bot/domain/entities/coordinates_sequence.py
quepland_bot/domain/enums/__init__.py
quepland_bot/domain/enums/command_key_enum.py
quepland_bot/domain/enums/keyboard_key_enum.py
quepland_bot/domain/exceptions/__init__.py
quepland_bot/domain/exceptions/coordinates_collection_empty_exception.py
quepland_bot/domain/exceptions/domain_exception.py
quepland_bot/domain/ports/__init__.py
quepland_bot/domain/ports/click_recorder_port.py
quepland_bot/domain/ports/mouse_loop_breaker_port.py
quepland_bot/domain/ports/mouse_port.py
quepland_bot/domain/use_cases/__init__.py
quepland_bot/domain/use_cases/click_on_coordinates_sequence_use_case.py
quepland_bot/domain/use_cases/record_clicks_use_case.py
quepland_bot/domain/value_objects/__init__.py
quepland_bot/domain/value_objects/coordinates.py
quepland_bot/infrastructure/__init__.py
quepland_bot/infrastructure/adapters/__init__.py
quepland_bot/infrastructure/adapters/pyautogui_mouse_adapter.py
quepland_bot/infrastructure/adapters/pynput_click_recorder/__init__.py
quepland_bot/infrastructure/adapters/pynput_click_recorder/pynput_click_recorder_adapter.py
quepland_bot/infrastructure/adapters/pynput_click_recorder/pynput_keymap.py
quepland_bot/infrastructure/adapters/pynput_mouse_loop_breaker_adapter.py
quepland_bot/quepland_bot.py
quepland_bot-0.1.6.dist-info/LICENSE
quepland_bot-0.1.6.dist-info/WHEEL
quepland_bot-0.1.6.dist-info/METADATA
quepland_bot-0.1.6.dist-info/RECORD
