Metadata-Version: 2.1
Name: quepland-bot
Version: 0.1.6
Summary: Simple library to record and play mouse macros at regular intervals between clicks.
Home-page: https://github.com/francisco-mascarenhas/quepland_bot
License: GPL3
Keywords: mouse,macro,automation,record
Author: Francisco Mascarenhas
Requires-Python: >=3.7,<4.0
Classifier: Development Status :: 2 - Pre-Alpha
Classifier: License :: OSI Approved :: GNU General Public License v3 (GPLv3)
Classifier: License :: Other/Proprietary License
Classifier: Operating System :: Unix
Classifier: Programming Language :: Python :: 3
Classifier: Programming Language :: Python :: 3.10
Classifier: Programming Language :: Python :: 3.7
Classifier: Programming Language :: Python :: 3.8
Classifier: Programming Language :: Python :: 3.9
Requires-Dist: PyAutoGUI (>=0.9.53,<0.10.0)
Requires-Dist: pynput (>=1.7.6,<2.0.0)
Project-URL: Repository, https://github.com/francisco-mascarenhas/quepland_bot
